ti_client_hive_1_ti_client/__init__.py
ti_client_hive_1_ti_client/api_client.py
ti_client_hive_1_ti_client/api_response.py
ti_client_hive_1_ti_client/configuration.py
ti_client_hive_1_ti_client/exceptions.py
ti_client_hive_1_ti_client/py.typed
ti_client_hive_1_ti_client/rest.py
ti_client_hive_1_ti_client/api/__init__.py
ti_client_hive_1_ti_client/api/gifs_api.py
ti_client_hive_1_ti_client/api/stickers_api.py
ti_client_hive_1_ti_client/models/__init__.py
ti_client_hive_1_ti_client/models/get_gifs_by_id200_response.py
ti_client_hive_1_ti_client/models/gif.py
ti_client_hive_1_ti_client/models/gif_images.py
ti_client_hive_1_ti_client/models/gif_images_downsized.py
ti_client_hive_1_ti_client/models/gif_images_downsized_large.py
ti_client_hive_1_ti_client/models/gif_images_downsized_medium.py
ti_client_hive_1_ti_client/models/gif_images_downsized_small.py
ti_client_hive_1_ti_client/models/gif_images_downsized_still.py
ti_client_hive_1_ti_client/models/gif_images_fixed_height.py
ti_client_hive_1_ti_client/models/gif_images_fixed_height_downsampled.py
ti_client_hive_1_ti_client/models/gif_images_fixed_height_small.py
ti_client_hive_1_ti_client/models/gif_images_fixed_height_small_still.py
ti_client_hive_1_ti_client/models/gif_images_fixed_height_still.py
ti_client_hive_1_ti_client/models/gif_images_fixed_width.py
ti_client_hive_1_ti_client/models/gif_images_fixed_width_downsampled.py
ti_client_hive_1_ti_client/models/gif_images_fixed_width_small.py
ti_client_hive_1_ti_client/models/gif_images_fixed_width_small_still.py
ti_client_hive_1_ti_client/models/gif_images_fixed_width_still.py
ti_client_hive_1_ti_client/models/gif_images_looping.py
ti_client_hive_1_ti_client/models/gif_images_original.py
ti_client_hive_1_ti_client/models/gif_images_original_still.py
ti_client_hive_1_ti_client/models/gif_images_preview.py
ti_client_hive_1_ti_client/models/gif_images_preview_gif.py
ti_client_hive_1_ti_client/models/image.py
ti_client_hive_1_ti_client/models/meta.py
ti_client_hive_1_ti_client-1.0.0.dist-info/METADATA
ti_client_hive_1_ti_client-1.0.0.dist-info/WHEEL
ti_client_hive_1_ti_client-1.0.0.dist-info/top_level.txt
ti_client_hive_1_ti_client-1.0.0.dist-info/RECORD
